pollination/ladybug_radiance/__init__.py
pollination/ladybug_radiance/direct_sunhours.py
pollination/ladybug_radiance/radiation.py
pollination/ladybug_radiance/scripts/direct_sunhours.py
pollination/ladybug_radiance/scripts/incident_radiation.py
pollination_ladybug_radiance-0.2.3.dist-info/LICENSE
pollination_ladybug_radiance-0.2.3.dist-info/METADATA
pollination_ladybug_radiance-0.2.3.dist-info/WHEEL
pollination_ladybug_radiance-0.2.3.dist-info/top_level.txt
pollination_ladybug_radiance-0.2.3.dist-info/RECORD
