Metadata-Version: 2.1
Name: pollination-ladybug-radiance
Version: 0.2.3
Summary: Ladybug Radiance plugin for Pollination.
Home-page: https://github.com/pollination/pollination-ladybug-radiance
Author: ladybug-tools
Author-email: info@ladybug.tools
Maintainer: mostapha, ladybug-tools
Maintainer-email: mostapha@ladybug.tools, info@ladybug.tools
License: PolyForm Shield License 1.0.0, https://polyformproject.org/wp-content/uploads/2020/06/PolyForm-Shield-1.0.0.txt
Project-URL: icon, https://raw.githubusercontent.com/ladybug-tools/artwork/master/icons_bugs/grasshopper_tabs/HB-Radiance.png
Project-URL: docker, https://hub.docker.com/r/ladybugtools/ladybug-radiance
Keywords: ladybug,radiance,ladybug-tools,daylight
Platform: UNKNOWN
Requires-Dist: pollination-dsl (>=0.15.0)
Requires-Dist: ladybug-radiance[display] (>=0.2.11)
